python_flaggle/__init__.py
python_flaggle/flag.py
python_flaggle/flaggle.py
python_flaggle-0.3.1.dist-info/LICENSE
python_flaggle-0.3.1.dist-info/METADATA
python_flaggle-0.3.1.dist-info/WHEEL
python_flaggle-0.3.1.dist-info/RECORD
