Metadata-Version: 2.3
Name: python_flaggle
Version: 0.3.1
Summary: python-flaggle is a Python library for feature flag management.
License: MIT
Keywords: feature flags,feature toggles,feature management,python
Author: Asaph Diniz
Author-email: contato@asaph.dev.br
Requires-Python: >=3.9
Classifier: Intended Audience :: Developers
Classifier: License :: OSI Approved :: MIT License
Classifier: Programming Language :: Python :: 3
Classifier: Programming Language :: Python :: 3.10
Classifier: Programming Language :: Python :: 3.11
Classifier: Programming Language :: Python :: 3.12
Classifier: Programming Language :: Python :: 3.13
Classifier: Topic :: Software Development :: Libraries
Requires-Dist: requests (>=2.32.3,<3.0.0)
Project-URL: Repo, https://github.com/Flaggle/flaggle-python
